{
  "kind": "singleType",
  "collectionName": "metas",
  "info": {
    "name": "Meta",
    "description": ""
  },
  "options": {
    "increments": true,
    "timestamps": true,
    "draftAndPublish": false
  },
  "pluginOptions": {},
  "attributes": {
    "title": {
      "type": "string"
    },
    "description": {
      "type": "string",
      "minLength": 50,
      "required": true,
      "maxLength": 150
    },
    "twitter": {
      "type": "string"
    },
    "github": {
      "type": "string"
    },
    "email": {
      "type": "email"
    },
    "vimeo": {
      "type": "string"
    },
    "youtube": {
      "type": "string"
    },
    "soundcloud": {
      "type": "string"
    },
    "instagram": {
      "type": "string"
    },
    "footer_text": {
      "type": "string"
    },
    "keywords": {
      "type": "string"
    },
    "error_title": {
      "type": "string"
    },
    "error_text": {
      "type": "string"
    }
  }
}
